atcbaselib/__init__.py
atcbaselib/common_rdm.py
atcbaselib/log_checker.py
atcbaselib/prepare_info.py
atcbaselib-0.0.3.data/data/logconfig.ini
atcbaselib-0.0.3.dist-info/METADATA
atcbaselib-0.0.3.dist-info/WHEEL
atcbaselib-0.0.3.dist-info/top_level.txt
atcbaselib-0.0.3.dist-info/RECORD
